skcyto/__init__.py
skcyto/_version.py
skcyto/consensuscluster.py
skcyto/flowsom.py
skcyto/preprocessing.py
skcyto/tests/__init__.py
skcyto/tests/test_common.py
skcyto/tests/test_consensuscluster.py
skcyto/tests/test_flowsom.py
skcyto/tests/test_preprocessing.py
skcyto-0.0.1.dist-info/LICENSE
skcyto-0.0.1.dist-info/METADATA
skcyto-0.0.1.dist-info/WHEEL
skcyto-0.0.1.dist-info/top_level.txt
skcyto-0.0.1.dist-info/RECORD
