Metadata-Version: 2.1
Name: skcyto
Version: 0.0.1
Summary: "Flow cytometry for sk-learn
Home-page: https://github.com/MSHelm/skcyto
Download-URL: https://github.com/MSHelm/skcyto
Maintainer: Martin Helm
Maintainer-email: martin@bio-ai.org
License: new BSD
License-File: LICENSE
Requires-Dist: numpy
Requires-Dist: scipy
Requires-Dist: scikit-learn (>=1.2.0)
Requires-Dist: minisom
Requires-Dist: igraph
Requires-Dist: flowutils
Provides-Extra: dev
Requires-Dist: pylint ; extra == 'dev'
Requires-Dist: pandas ; extra == 'dev'
Provides-Extra: docs
Requires-Dist: sphinx ; extra == 'docs'
Requires-Dist: sphinx-gallery ; extra == 'docs'
Requires-Dist: sphinx-rtd-theme ; extra == 'docs'
Requires-Dist: numpydoc ; extra == 'docs'
Requires-Dist: matplotlib ; extra == 'docs'
Provides-Extra: tests
Requires-Dist: pytest ; extra == 'tests'
Requires-Dist: pytest-cov ; extra == 'tests'
